tractags/__init__.py
tractags/admin.py
tractags/api.py
tractags/db.py
tractags/db_default.py
tractags/macros.py
tractags/model.py
tractags/query.py
tractags/ticket.py
tractags/util.py
tractags/web_ui.py
tractags/wiki.py
tractags/wikiautocomplete.py
tractags/xmlrpc.py
tractags/htdocs/css/tractags.css
tractags/htdocs/js/autocomplete_tags.js
tractags/locale/.placeholder
tractags/templates/admin_tag_change.html
tractags/templates/listtagged_results.html
tractags/templates/tag_view.html
tractags/upgrades/__init__.py
tractags/upgrades/db2.py
tractags/upgrades/db3.py
tractags/upgrades/db4.py
TracTags-0.12.1.dist-info/COPYING
TracTags-0.12.1.dist-info/METADATA
TracTags-0.12.1.dist-info/WHEEL
TracTags-0.12.1.dist-info/entry_points.txt
TracTags-0.12.1.dist-info/top_level.txt
TracTags-0.12.1.dist-info/RECORD
